nimview/__init__.py
nimview/nimview.pyd
nimview-0.3.2.dist-info/METADATA
nimview-0.3.2.dist-info/WHEEL
nimview-0.3.2.dist-info/top_level.txt
nimview-0.3.2.dist-info/RECORD
